mars_vectorizer_sdk/__init__.py
mars_vectorizer_sdk-0.2.0.dist-info/METADATA
mars_vectorizer_sdk-0.2.0.dist-info/WHEEL
mars_vectorizer_sdk-0.2.0.dist-info/RECORD
