Metadata-Version: 2.1
Name: mars-vectorizer-sdk
Version: 0.2.0
Summary: 
Author: znittzel
Author-email: rikard@ourstudio.se
Requires-Python: >=3.9,<4.0
Classifier: Programming Language :: Python :: 3
Classifier: Programming Language :: Python :: 3.9
Classifier: Programming Language :: Python :: 3.10
Classifier: Programming Language :: Python :: 3.11
Classifier: Programming Language :: Python :: 3.12
Requires-Dist: numpy (>=1.26.4,<2.0.0)
